servicex_client/__init__.py
servicex_client/_version.py
servicex_client/app/__init__.py
servicex_client/app/cache.py
servicex_client/app/cli_options.py
servicex_client/app/main.py
servicex_client/app/transforms.py
servicex_client/configuration.py
servicex_client/dataset_identifier.py
servicex_client/func_adl/__init__.py
servicex_client/func_adl/servicex_dataset_source.py
servicex_client/func_adl/servicex_func_adl_uproot.py
servicex_client/func_adl/util.py
servicex_client/minio_adpater.py
servicex_client/models.py
servicex_client/query_cache.py
servicex_client/servicex_adapter.py
servicex_client/servicex_client.py
servicex_client-0.1.0.dist-info/entry_points.txt
servicex_client-0.1.0.dist-info/LICENSE
servicex_client-0.1.0.dist-info/WHEEL
servicex_client-0.1.0.dist-info/METADATA
servicex_client-0.1.0.dist-info/RECORD
